<?xml version="1.0" ?>
<document>
	<sentence>
		Thử thách trí tuệ nhân tạo AI Challenge 2023.
		<word>thử thách trí tuệ</word>
		<word>nhân tạo</word>
		<word>challenge</word>
		<word>2023</word>
	</sentence>
	<sentence>
		Hội thi Thử thách trí tuệ nhân tạo (AI Challenge) TP.HCM năm 2023 nhằm tìm kiếm và ứng dụng các giải pháp trí tuệ nhân tạo, giúp Thành phố giải quyết các bài toán đầu tư, phát triển và xây dựng đô thị thông minh….
		<word>hội</word>
		<word>thi</word>
		<word>thử thách trí tuệ</word>
		<word>nhân tạo</word>
		<word>ai challenge</word>
		<word>tp.hcm</word>
		<word>2023</word>
		<word>tìm kiếm</word>
		<word>ứng dụng</word>
		<word>giải pháp</word>
		<word>trí tuệ</word>
		<word>nhân tạo</word>
		<word>giúp</word>
		<word>thành phố</word>
		<word>giải quyết</word>
		<word>bài toán</word>
		<word>đầu tư</word>
		<word>phát triển</word>
		<word>xây dựng</word>
		<word>đô thị</word>
		<word>thông minh</word>
		<word>…</word>
	</sentence>
	<sentence>
		Theo Sở Thông tin và Truyền thông TP.HCM, đối tượng tham gia hội thi là cá nhân người Việt Nam ở trong và ngoài nước (bao gồm cả người Việt Nam ở nước ngoài), người nước ngoài đang sinh sống, học tập, làm việc tại Việt Nam đều có thể đăng ký tham gia dự thi.
		<word>sở</word>
		<word>thông tin</word>
		<word>truyền thông</word>
		<word>tp.hcm</word>
		<word>đối tượng</word>
		<word>tham gia</word>
		<word>hội</word>
		<word>thi</word>
		<word>việt nam</word>
		<word>bao gồm</word>
		<word>việt nam</word>
		<word>nước ngoài</word>
		<word>nước ngoài</word>
		<word>sinh sống</word>
		<word>học tập</word>
		<word>làm việc</word>
		<word>việt nam</word>
		<word>đăng ký</word>
		<word>tham gia</word>
		<word>dự</word>
		<word>thi</word>
	</sentence>
	<sentence>
		Hội thi được chia thành 2 bảng.
		<word>hội</word>
		<word>thi</word>
		<word>chia</word>
		<word>thành</word>
		<word>2</word>
		<word>bảng</word>
	</sentence>
	<sentence>
		Trong đó, bảng A dành cho sinh viên, thanh niên có quan tâm đến lĩnh vực công nghệ thông tin, trí tuệ nhân tạo và bảng B dành cho học sinh các trường trung học phổ thông trên địa bàn TP.HCM yêu thích công nghệ thông tin và muốn tìm hiểu về trí tuệ nhân tạo.
		<word>bảng a</word>
		<word>sinh viên</word>
		<word>thanh niên</word>
		<word>lĩnh vực</word>
		<word>công nghệ thông tin</word>
		<word>trí tuệ</word>
		<word>nhân tạo</word>
		<word>bảng</word>
		<word>b</word>
		<word>học sinh</word>
		<word>trường</word>
		<word>trung học phổ thông</word>
		<word>địa bàn</word>
		<word>tp.hcm</word>
		<word>yêu thích</word>
		<word>công nghệ thông tin</word>
		<word>trí tuệ</word>
		<word>nhân tạo</word>
	</sentence>
	<sentence>
		Về nội dung thi, các thí sinh tham dự sẽ phát triển các thuật toán trí tuệ nhân tạo để giải quyết bài toán trong cuộc sống, ứng dụng phục vụ cho TP.HCM theo chủ đề của cuộc thi.
		<word>nội dung</word>
		<word>thi</word>
		<word>thí sinh</word>
		<word>tham dự</word>
		<word>phát triển</word>
		<word>thuật toán</word>
		<word>trí tuệ</word>
		<word>nhân tạo</word>
		<word>giải quyết</word>
		<word>bài toán</word>
		<word>cuộc sống</word>
		<word>ứng dụng</word>
		<word>phục vụ</word>
		<word>tp.hcm</word>
		<word>chủ đề</word>
		<word>thi</word>
	</sentence>
	<sentence>
		Cuộc thi được tổ chức theo hình thức cuộc thi khoa học, tương tự các cuộc thi (challenge) thường được tổ chức trên thế giới nhằm tìm kiếm các giải pháp hiệu quả cho các vấn đề mới đang được quan tâm nhằm phục vụ cuộc sống.
		<word>thi</word>
		<word>tổ chức</word>
		<word>hình thức</word>
		<word>thi</word>
		<word>khoa học</word>
		<word>tương tự</word>
		<word>thi</word>
		<word>challenge</word>
		<word>tổ chức</word>
		<word>thế giới</word>
		<word>tìm kiếm</word>
		<word>giải pháp</word>
		<word>hiệu quả</word>
		<word>phục vụ</word>
		<word>cuộc sống</word>
	</sentence>
	<sentence>
		Trong đó, bài toán dự kiến là truy vấn sự kiện từ video, thể thức tương tự cuộc thi quốc tế Lifelog Search Challenge (LSC) và Video Browser Showdown (VBS).
		<word>bài toán</word>
		<word>dự kiến</word>
		<word>truy vấn</word>
		<word>sự kiện</word>
		<word>video</word>
		<word>thể thức</word>
		<word>tương tự</word>
		<word>thi</word>
		<word>quốc tế</word>
		<word>lifelog search</word>
		<word>challenge</word>
		<word>lsc</word>
		<word>video</word>
		<word>browser showdown</word>
		<word>vbs</word>
	</sentence>
	<sentence>
		Riêng đối với thí sinh bảng B được phép sử dụng công cụ có sẵn do Ban tổ chức cung cấp để thực hiện các yêu cầu của cuộc thi đưa ra.
		<word>thí sinh</word>
		<word>bảng</word>
		<word>b</word>
		<word>phép</word>
		<word>công cụ</word>
		<word>sẵn</word>
		<word>ban</word>
		<word>tổ chức</word>
		<word>cung cấp</word>
		<word>thi</word>
	</sentence>
	<sentence>
		Sau khi đăng ký tham dự cuộc thi, thí sinh được tập huấn kiến thức về các nội dung theo chủ đề cuộc thi.
		<word>đăng ký</word>
		<word>tham dự</word>
		<word>thi</word>
		<word>thí sinh</word>
		<word>tập huấn</word>
		<word>kiến thức</word>
		<word>nội dung</word>
		<word>chủ đề</word>
		<word>thi</word>
	</sentence>
	<sentence>
		Sở Thông tin và Truyền thông TP.HCM cho biết, tiêu chí đánh giá dựa trên các thuật toán, sản phẩm tham gia hội thi phải có hàm lượng khoa học cao, có tính cập nhật; giải quyết được những vấn đề cụ thể theo chủ đề đặt ra.
		<word>sở</word>
		<word>thông tin</word>
		<word>truyền thông</word>
		<word>tp.hcm</word>
		<word>tiêu chí</word>
		<word>dựa</word>
		<word>thuật toán</word>
		<word>sản phẩm</word>
		<word>tham gia</word>
		<word>hội</word>
		<word>thi</word>
		<word>hàm lượng</word>
		<word>khoa học</word>
		<word>cập nhật</word>
		<word>giải quyết</word>
		<word>chủ đề</word>
	</sentence>
	<sentence>
		Đồng thời, kết quả được đánh giá trên các bộ test của Ban tổ chức, có sự thẩm định kết quả của Hội đồng giám khảo.
		<word>kết quả</word>
		<word>bộ test</word>
		<word>ban</word>
		<word>tổ chức</word>
		<word>thẩm định</word>
		<word>kết quả</word>
		<word>hội đồng</word>
		<word>giám khảo</word>
	</sentence>
	<sentence>
		Ngoài ra, Ban tổ chức còn cho biết việc tổ chức cuộc thi nhằm tìm kiếm và ứng dụng các giải pháp sử dụng trí tuệ nhân tạo giúp giải quyết các bài toán được đặt ra trong bối cảnh thành phố đang tập trung đầu tư phát triển và đẩy mạnh xây dựng đô thị thông minh.
		<word>ban</word>
		<word>tổ chức</word>
		<word>tổ chức</word>
		<word>thi</word>
		<word>tìm kiếm</word>
		<word>ứng dụng</word>
		<word>giải pháp</word>
		<word>trí tuệ</word>
		<word>nhân tạo</word>
		<word>giúp</word>
		<word>giải quyết</word>
		<word>bài toán</word>
		<word>bối cảnh</word>
		<word>thành phố</word>
		<word>đầu tư</word>
		<word>phát triển</word>
		<word>đẩy mạnh</word>
		<word>xây dựng</word>
		<word>đô thị</word>
		<word>thông minh</word>
	</sentence>
	<sentence>
		Hình thức khen thưởng sẽ gồm cúp, giấy khen của Ban tổ chức, tiền thưởng với tổng giá trị giải thưởng lên đến 200 triệu đồng.
		<word>hình thức</word>
		<word>khen thưởng</word>
		<word>cúp</word>
		<word>giấy</word>
		<word>khen</word>
		<word>ban</word>
		<word>tổ chức</word>
		<word>tiền</word>
		<word>thưởng</word>
		<word>tổng</word>
		<word>giải thưởng</word>
		<word>200</word>
		<word>triệu</word>
		<word>đồng</word>
	</sentence>
	<sentence>
		Được biết, phương pháp của các đội đạt kết quả tốt trong hội thi, qua quá trình phản biện của các chuyên gia trong nước và quốc tế, sẽ được chọn và mời trình bày trong Special Session về Lifelog and Multimedia Event Retrieval trong Hội thảo quốc tế The 12th International Symposium on Information and Communication Technology (SoICT 2023), được tổ chức từ vào ngày 7 và 8/12/2023 tại TP.HCM, đồng thời được đăng trong kỷ yếu hội thảo do ACM xuất bản.
		<word>phương pháp</word>
		<word>đội</word>
		<word>kết quả</word>
		<word>hội</word>
		<word>thi</word>
		<word>phản biện</word>
		<word>chuyên gia</word>
		<word>quốc tế</word>
		<word>mời</word>
		<word>trình bày</word>
		<word>special session</word>
		<word>lifelog and</word>
		<word>multimedia</word>
		<word>event retrieval</word>
		<word>hội thảo</word>
		<word>quốc tế</word>
		<word>the</word>
		<word>12</word>
		<word>th international</word>
		<word>symposium on</word>
		<word>information and</word>
		<word>communication technology</word>
		<word>soict</word>
		<word>2023</word>
		<word>tổ chức</word>
		<word>7</word>
		<word>8/12/2023</word>
		<word>tp.hcm</word>
		<word>đăng</word>
		<word>kỷ yếu</word>
		<word>hội thảo</word>
		<word>acm</word>
		<word>xuất bản</word>
	</sentence>
	<sentence>
		Đặc biệt, những giải pháp đạt giải sẽ được hỗ trợ kết nối giới thiệu thuật toán, giải pháp tới các đơn vị đang triển khai chính quyền điện tử, đô thị thông minh (nếu cá nhân, đơn vị đạt giải có nhu cầu) và được tạo điều kiện thuận lợi để đăng ký các giải pháp hữu ích, vườn ươm sản phẩm tiềm năng từ thuật toán, giải pháp đạt giải.
		<word>giải pháp</word>
		<word>giải</word>
		<word>kết nối</word>
		<word>giới thiệu</word>
		<word>thuật toán</word>
		<word>giải pháp</word>
		<word>triển khai</word>
		<word>chính quyền</word>
		<word>điện tử</word>
		<word>đô thị</word>
		<word>thông minh</word>
		<word>giải</word>
		<word>nhu cầu</word>
		<word>thuận lợi</word>
		<word>đăng ký</word>
		<word>giải pháp</word>
		<word>hữu ích</word>
		<word>vườn ươm</word>
		<word>sản phẩm</word>
		<word>tiềm năng</word>
		<word>thuật toán</word>
		<word>giải pháp</word>
		<word>giải</word>
	</sentence>
</document>
