<?xml version="1.0" ?>
<document>
	<sentence>
		Vinh danh những tác giả, tác phẩm báo chí xuất sắc về khoa học công nghệ.
		<word>vinh danh</word>
		<word>tác giả</word>
		<word>tác phẩm</word>
		<word>báo chí</word>
		<word>xuất sắc</word>
		<word>khoa học</word>
		<word>công nghệ</word>
	</sentence>
	<sentence>
		Với loạt tác phẩm về “Phát triển khoa học công nghệ: Cơ chế đặc thù và “chìa khóa” vốn”, Tạp chí Kinh tế Việt Nam đã được trao giải Nhất Giải thưởng báo chí về khoa học công nghệ năm 2023 cho thể loại báo in.
		<word>loạt</word>
		<word>tác phẩm</word>
		<word>“</word>
		<word>phát triển</word>
		<word>khoa học</word>
		<word>công nghệ</word>
		<word>cơ chế</word>
		<word>đặc thù</word>
		<word>“</word>
		<word>chìa khóa</word>
		<word>”</word>
		<word>vốn</word>
		<word>”</word>
		<word>tạp chí</word>
		<word>kinh tế</word>
		<word>việt nam</word>
		<word>trao</word>
		<word>giải nhất</word>
		<word>giải thưởng</word>
		<word>báo chí</word>
		<word>khoa học</word>
		<word>công nghệ</word>
		<word>2023</word>
		<word>thể loại</word>
		<word>báo</word>
		<word>in</word>
	</sentence>
	<sentence>
		Đây cũng là năm thứ 2 liên tiếp, các tác phẩm của Tạp chí Kinh tế Việt Nam dành giải thưởng cao nhất.... Ngày 16/5/2024, tại Hà Nội, Bộ Khoa học và Công nghệ trao Giải thưởng báo chí về khoa học và công nghệ năm 2023, vinh danh 68 tác giả của 23 tác phẩm/nhóm tác phẩm của 5 loại hình báo chí.
		<word>2</word>
		<word>liên tiếp</word>
		<word>tác phẩm</word>
		<word>tạp chí</word>
		<word>kinh tế</word>
		<word>việt nam</word>
		<word>giải thưởng</word>
		<word>....</word>
		<word>16/5/2024</word>
		<word>hà nội</word>
		<word>bộ khoa học và</word>
		<word>công nghệ</word>
		<word>trao</word>
		<word>giải thưởng</word>
		<word>báo chí</word>
		<word>khoa học</word>
		<word>công nghệ</word>
		<word>2023</word>
		<word>vinh danh</word>
		<word>68</word>
		<word>tác giả</word>
		<word>23</word>
		<word>tác phẩm</word>
		<word>tác phẩm</word>
		<word>5</word>
		<word>loại hình</word>
		<word>báo chí</word>
	</sentence>
	<sentence>
		Giải thưởng báo chí về khoa học và công nghệ được Bộ Khoa học và Công nghệ tổ chức hằng năm nhằm tôn vinh các tác giả có tác phẩm báo chí xuất sắc về khoa học và công nghệ.
		<word>giải thưởng</word>
		<word>báo chí</word>
		<word>khoa học</word>
		<word>công nghệ</word>
		<word>khoa học và</word>
		<word>công nghệ</word>
		<word>tổ chức</word>
		<word>hằng</word>
		<word>tôn vinh</word>
		<word>tác giả</word>
		<word>tác phẩm</word>
		<word>báo chí</word>
		<word>xuất sắc</word>
		<word>khoa học</word>
		<word>công nghệ</word>
	</sentence>
	<sentence>
		Đây là sự ghi nhận của Bộ Khoa học và Công nghệ trong việc vinh danh những nhà báo có tinh thần khoa học, đã nỗ lực hết mình, tìm tòi, phát hiện, phản ánh các kết quả của hoạt động khoa học công nghệ trong sự phát triển của đất nước.
		<word>ghi nhận</word>
		<word>khoa học và</word>
		<word>công nghệ</word>
		<word>vinh danh</word>
		<word>nhà báo</word>
		<word>tinh thần</word>
		<word>khoa học</word>
		<word>nỗ lực</word>
		<word>hết mình</word>
		<word>tìm tòi</word>
		<word>phát hiện</word>
		<word>phản ánh</word>
		<word>kết quả</word>
		<word>hoạt động</word>
		<word>khoa học</word>
		<word>công nghệ</word>
		<word>phát triển</word>
		<word>đất nước</word>
	</sentence>
	<sentence>
		Thứ trưởng Bộ Khoa học và Công nghệ Nguyễn Hoàng Giang nhấn mạnh, Giải thưởng là dịp để Bộ Khoa học và Công nghệ tri ân, tôn vinh các nhà báo luôn đồng hành, dõi theo quá trình phát triển, những bước đi của ngành khoa học và công nghệ, nỗ lực hết mình, tìm tòi, phát hiện, phản ánh các lĩnh vực hoạt động của ngành.
		<word>thứ trưởng</word>
		<word>khoa học và</word>
		<word>công nghệ</word>
		<word>nguyễn hoàng giang</word>
		<word>nhấn mạnh</word>
		<word>giải thưởng</word>
		<word>dịp</word>
		<word>khoa học và</word>
		<word>công nghệ</word>
		<word>tri ân</word>
		<word>tôn vinh</word>
		<word>nhà báo</word>
		<word>đồng hành</word>
		<word>dõi</word>
		<word>phát triển</word>
		<word>ngành</word>
		<word>khoa học</word>
		<word>công nghệ</word>
		<word>nỗ lực</word>
		<word>hết mình</word>
		<word>tìm tòi</word>
		<word>phát hiện</word>
		<word>phản ánh</word>
		<word>lĩnh vực</word>
		<word>hoạt động</word>
		<word>ngành</word>
	</sentence>
	<sentence>
		Sau hơn 10 năm triển khai tổ chức, Giải thưởng Báo chí về Khoa học và Công nghệ ghi dấu ấn theo hướng ngày càng chuyên nghiệp, sức lan tỏa lớn hơn, chất lượng các tác phẩm dự thi ngày càng cao.
		<word>10</word>
		<word>triển khai</word>
		<word>tổ chức</word>
		<word>giải thưởng</word>
		<word>báo chí</word>
		<word>khoa học và</word>
		<word>công nghệ</word>
		<word>ghi</word>
		<word>dấu ấn</word>
		<word>hướng</word>
		<word>chuyên nghiệp</word>
		<word>sức</word>
		<word>lan tỏa</word>
		<word>chất lượng</word>
		<word>tác phẩm</word>
		<word>dự</word>
		<word>thi</word>
	</sentence>
	<sentence>
		Bằng sự ghi nhận thực tế, sự dấn thân, các nhà báo đã tạo ra những tác phẩm chân thực, khách quan, phản ánh một cách toàn diện, đa chiều các lĩnh vực hoạt động Khoa học công nghệ và Đổi mới sáng tạo.
		<word>ghi nhận</word>
		<word>dấn thân</word>
		<word>nhà báo</word>
		<word>tác phẩm</word>
		<word>chân thực</word>
		<word>khách quan</word>
		<word>phản ánh</word>
		<word>toàn diện</word>
		<word>đa chiều</word>
		<word>lĩnh vực</word>
		<word>hoạt động</word>
		<word>khoa học</word>
		<word>công nghệ</word>
		<word>đổi mới</word>
		<word>sáng tạo</word>
	</sentence>
	<sentence>
		Đó là sự đổi mới về tư duy, cách nghĩ, cách làm trong xây dựng và thực thi chính sách phát triển Khoa học công nghệ và Đổi mới sáng tạo; những kết quả đóng góp của khoa học công nghệ và đổi mới sáng tạo vào sự nâng cao năng suất, chất lượng và sức cạnh tranh của nền kinh tế, giải quyết các bài toán của thực tiễn cuộc sống; những tấm gương nhà khoa học tận tụy, đam mê nghiên cứu, sáng tạo; các công nghệ, kỹ thuật hiện đại được ứng dụng vào thực tiễn đời sống, sản xuất, giúp giải phóng sức lao động của con người, hiện đại hóa cuộc sống của người dân…, Thứ trưởng nói.
		<word>đổi mới</word>
		<word>tư duy</word>
		<word>xây dựng</word>
		<word>thực thi</word>
		<word>chính sách</word>
		<word>phát triển</word>
		<word>khoa học</word>
		<word>công nghệ</word>
		<word>đổi mới</word>
		<word>sáng tạo</word>
		<word>kết quả</word>
		<word>đóng góp</word>
		<word>khoa học</word>
		<word>công nghệ</word>
		<word>đổi mới</word>
		<word>sáng tạo</word>
		<word>nâng</word>
		<word>năng suất</word>
		<word>chất lượng</word>
		<word>sức</word>
		<word>cạnh tranh</word>
		<word>kinh tế</word>
		<word>giải quyết</word>
		<word>bài toán</word>
		<word>thực tiễn</word>
		<word>cuộc sống</word>
		<word>gương</word>
		<word>nhà khoa học</word>
		<word>tận tụy</word>
		<word>đam mê</word>
		<word>nghiên cứu</word>
		<word>sáng tạo</word>
		<word>công nghệ</word>
		<word>kỹ thuật</word>
		<word>hiện đại</word>
		<word>ứng dụng</word>
		<word>thực tiễn</word>
		<word>đời sống</word>
		<word>sản xuất</word>
		<word>giúp</word>
		<word>giải phóng</word>
		<word>sức lao động</word>
		<word>con người</word>
		<word>hiện đại hóa</word>
		<word>cuộc sống</word>
		<word>người dân</word>
		<word>…</word>
		<word>thứ trưởng</word>
	</sentence>
	<sentence>
		Năm 2023, đã có hàng nghìn tin, bài, phóng sự, tọa đàm... liên quan đến các lĩnh vực hoạt động của Khoa học và Công nghệ đã được đăng tải trên các phương tiện truyền thông đại chúng.
		<word>2023</word>
		<word>hàng</word>
		<word>nghìn</word>
		<word>phóng sự</word>
		<word>tọa đàm</word>
		<word>...</word>
		<word>lĩnh vực</word>
		<word>hoạt động</word>
		<word>khoa học và</word>
		<word>công nghệ</word>
		<word>đăng tải</word>
		<word>phương tiện</word>
		<word>truyền thông</word>
		<word>đại chúng</word>
	</sentence>
	<sentence>
		Mỗi tác phẩm là một mảnh ghép trong bức tranh toàn cảnh của hoạt động Khoa học công nghệ và Đổi mới sáng tạo, lan tỏa thông tin và tình yêu khoa học và công nghệ, sự say mê sáng tạo.
		<word>tác phẩm</word>
		<word>mảnh</word>
		<word>ghép</word>
		<word>tranh</word>
		<word>toàn cảnh</word>
		<word>hoạt động</word>
		<word>khoa học</word>
		<word>công nghệ</word>
		<word>đổi mới</word>
		<word>sáng tạo</word>
		<word>lan tỏa</word>
		<word>thông tin</word>
		<word>tình yêu</word>
		<word>khoa học</word>
		<word>công nghệ</word>
		<word>say mê</word>
		<word>sáng tạo</word>
	</sentence>
	<sentence>
		Đây cũng là kênh thông tin quan trọng để các nhà hoạch định chính sách đưa ra những quyết sách quan trọng, sát với thực tiễn hoặc điều chỉnh chính sách nhằm thúc đẩy hoạt động Khoa học công nghệ và Đổi mới sáng tạo.
		<word>kênh</word>
		<word>thông tin</word>
		<word>nhà hoạch định</word>
		<word>chính sách</word>
		<word>quyết sách</word>
		<word>sát</word>
		<word>thực tiễn</word>
		<word>điều chỉnh</word>
		<word>chính sách</word>
		<word>thúc đẩy</word>
		<word>hoạt động</word>
		<word>khoa học</word>
		<word>công nghệ</word>
		<word>đổi mới</word>
		<word>sáng tạo</word>
	</sentence>
	<sentence>
		Biểu dương, chúc mừng 68 tác giả của 23 tác phẩm/nhóm tác phẩm của 5 loại hình báo chí: báo in, báo điện tử, báo phát thanh, báo truyền hình và báo ảnh đã đạt giải, Thứ trưởng Nguyễn Hoàng Giang khẳng định, đây là những tác phẩm/nhóm tác phẩm hội tụ được nhiều yếu tố xuất sắc, được các tác giả đầu tư công phu và có ảnh hưởng tích cực đối với đời sống xã hội, thu hút sự quan tâm của dư luận xã hội đã được hội đồng các cấp đánh giá, lựa chọn.
		<word>biểu dương</word>
		<word>chúc mừng</word>
		<word>68</word>
		<word>tác giả</word>
		<word>23</word>
		<word>tác phẩm</word>
		<word>tác phẩm</word>
		<word>5</word>
		<word>loại hình</word>
		<word>báo chí</word>
		<word>báo</word>
		<word>in</word>
		<word>báo điện tử</word>
		<word>báo</word>
		<word>phát thanh</word>
		<word>báo</word>
		<word>truyền hình</word>
		<word>báo</word>
		<word>ảnh</word>
		<word>giải</word>
		<word>thứ trưởng</word>
		<word>nguyễn hoàng giang</word>
		<word>tác phẩm</word>
		<word>tác phẩm</word>
		<word>hội tụ</word>
		<word>yếu tố</word>
		<word>xuất sắc</word>
		<word>tác giả</word>
		<word>đầu tư</word>
		<word>công phu</word>
		<word>ảnh hưởng</word>
		<word>tích cực</word>
		<word>đời sống</word>
		<word>xã hội</word>
		<word>thu hút</word>
		<word>dư luận</word>
		<word>xã hội</word>
		<word>hội đồng</word>
		<word>lựa chọn</word>
	</sentence>
	<sentence>
		Giải thưởng báo chí Khoa học và Công nghệ năm 2023 tiếp tục nhận được sự hưởng ứng tham gia của nhiều cơ quan báo chí ở trung ương và địa phương.
		<word>giải thưởng</word>
		<word>báo chí</word>
		<word>khoa học và</word>
		<word>công nghệ</word>
		<word>2023</word>
		<word>hưởng ứng</word>
		<word>tham gia</word>
		<word>cơ quan</word>
		<word>báo chí</word>
		<word>trung ương</word>
		<word>địa phương</word>
	</sentence>
	<sentence>
		Theo đánh giá của Hội đồng xét tặng, các tác phẩm đã phản ánh về mọi mặt hoạt động khoa học công nghệ của các nhà khoa học, các địa phương, doanh nghiệp cũng như của người dân; đi vào các nội dung cấp bách và thực tiễn của đời sống kinh tế xã hội.
		<word>hội đồng</word>
		<word>xét</word>
		<word>tặng</word>
		<word>tác phẩm</word>
		<word>phản ánh</word>
		<word>mặt</word>
		<word>hoạt động</word>
		<word>khoa học</word>
		<word>công nghệ</word>
		<word>nhà khoa học</word>
		<word>địa phương</word>
		<word>doanh nghiệp</word>
		<word>người dân</word>
		<word>đi</word>
		<word>nội dung</word>
		<word>cấp bách</word>
		<word>thực tiễn</word>
		<word>đời sống</word>
		<word>kinh tế</word>
		<word>xã hội</word>
	</sentence>
	<sentence>
		Một số tác phẩm có chất lượng tốt, bài viết thể hiện công phu sâu sắc về chủ đề có tính thời sự, các đánh giá bình luận phản ánh được yêu cầu và tác động của hoạt động khoa học và công nghệ.
		<word>tác phẩm</word>
		<word>chất lượng</word>
		<word>viết</word>
		<word>thể hiện</word>
		<word>công phu</word>
		<word>sâu sắc</word>
		<word>chủ đề</word>
		<word>thời sự</word>
		<word>bình luận</word>
		<word>phản ánh</word>
		<word>tác động</word>
		<word>hoạt động</word>
		<word>khoa học</word>
		<word>công nghệ</word>
	</sentence>
	<sentence>
		Năm qua, báo chí cũng tập trung phản ánh kịp thời, đậm nét kết quả hoạt động, sự kiện lớn của Bộ, của ngành khoa học và công nghệ, các chủ đề mang tính thời sự như: Xây dựng cơ chế chính sách nhằm tháo gỡ các nút thắt đẩy nhanh phát triển khoa học và công nghệ; Tác động của cuộc cách mạng công nghiệp lần thứ 4 với đời sống xã hội; Chuyển đổi số; Trí tuệ nhân tạo; Khởi nghiệp đổi mới sáng tạo...

Bộ Khoa học và Công nghệ cho biết thông qua các tác phẩm, vai trò, vị trí của khoa học và công nghệ được khẳng định trong việc tham gia giải quyết tốt các vấn đề thực tiễn cuộc sống đặt ra như: Nhóm tác phẩm: Phát triển khoa học, công nghệ: Cơ chế đặc thù và &quot;chìa khóa&quot; vốn; Gói tin tức đa phương tiện &quot;Trí tuệ nhân tạo Việt Nam&quot;; Khoa học công nghệ- Điểm tựa để nông nghiệp vững vai trò &quot;trụ đỡ&quot;; Hồi sinh; Rác thải cho tiền tỷ…

Ông Nguyễn Đức Lợi, Phó Chủ tịch Thường trực Hội Nhà báo Việt Nam, Chủ tịch Hội đồng Chung khảo Giải thưởng báo chí về Khoa học và Công nghệ năm 2023, cho biết năm 2023, ghi nhận những nỗ lực sáng tạo từ hình thức đến nội dung của các tác phẩm dự thi, các chuyên mục chuyên sâu về khoa học và công nghệ trên các báo mang một sức sống mới.
		<word>báo chí</word>
		<word>phản ánh</word>
		<word>kịp thời</word>
		<word>đậm nét</word>
		<word>kết quả</word>
		<word>hoạt động</word>
		<word>sự kiện</word>
		<word>ngành</word>
		<word>khoa học</word>
		<word>công nghệ</word>
		<word>chủ đề</word>
		<word>thời sự</word>
		<word>xây dựng</word>
		<word>cơ chế</word>
		<word>chính sách</word>
		<word>tháo gỡ</word>
		<word>nút</word>
		<word>thắt</word>
		<word>đẩy</word>
		<word>phát triển</word>
		<word>khoa học</word>
		<word>công nghệ</word>
		<word>tác động</word>
		<word>cách mạng</word>
		<word>công nghiệp</word>
		<word>4</word>
		<word>đời sống</word>
		<word>xã hội</word>
		<word>chuyển đổi</word>
		<word>trí tuệ</word>
		<word>nhân tạo</word>
		<word>khởi nghiệp</word>
		<word>đổi mới</word>
		<word>sáng tạo</word>
		<word>...</word>
		<word>khoa học và</word>
		<word>công nghệ</word>
		<word>thông qua</word>
		<word>tác phẩm</word>
		<word>vai trò</word>
		<word>khoa học</word>
		<word>công nghệ</word>
		<word>tham gia</word>
		<word>giải quyết</word>
		<word>thực tiễn</word>
		<word>cuộc sống</word>
		<word>tác phẩm</word>
		<word>phát triển</word>
		<word>khoa học</word>
		<word>công nghệ</word>
		<word>cơ chế</word>
		<word>đặc thù</word>
		<word>chìa</word>
		<word>khóa</word>
		<word>vốn</word>
		<word>gói</word>
		<word>tin tức</word>
		<word>đa</word>
		<word>phương tiện</word>
		<word>trí tuệ</word>
		<word>nhân tạo</word>
		<word>việt nam</word>
		<word>khoa học</word>
		<word>công nghệ</word>
		<word>điểm tựa</word>
		<word>nông nghiệp</word>
		<word>vững</word>
		<word>vai trò</word>
		<word>trụ</word>
		<word>đỡ</word>
		<word>hồi sinh</word>
		<word>rác thải</word>
		<word>tiền</word>
		<word>tỷ</word>
		<word>…</word>
		<word>nguyễn đức lợi</word>
		<word>phó</word>
		<word>chủ tịch</word>
		<word>thường trực</word>
		<word>hội</word>
		<word>nhà báo</word>
		<word>việt nam</word>
		<word>chủ tịch</word>
		<word>hội đồng</word>
		<word>chung khảo</word>
		<word>giải thưởng</word>
		<word>báo chí</word>
		<word>khoa học và</word>
		<word>công nghệ</word>
		<word>2023</word>
		<word>2023</word>
		<word>ghi nhận</word>
		<word>nỗ lực</word>
		<word>sáng tạo</word>
		<word>hình thức</word>
		<word>nội dung</word>
		<word>tác phẩm</word>
		<word>dự</word>
		<word>thi</word>
		<word>chuyên mục</word>
		<word>chuyên sâu</word>
		<word>khoa học</word>
		<word>công nghệ</word>
		<word>báo</word>
		<word>sức sống</word>
	</sentence>
	<sentence>
		Nội dung các tác phẩm báo chí viết về khoa học công nghệ được lựa chọn xuất phát từ hơi thở của đời sống và đến được với nhiều đối tượng độc giả.
		<word>nội dung</word>
		<word>tác phẩm</word>
		<word>báo chí</word>
		<word>viết</word>
		<word>khoa học</word>
		<word>công nghệ</word>
		<word>lựa chọn</word>
		<word>xuất phát</word>
		<word>hơi</word>
		<word>thở</word>
		<word>đời sống</word>
		<word>đối tượng</word>
		<word>độc giả</word>
	</sentence>
	<sentence>
		Bên cạnh đó, nhiều cơ quan báo chí và người làm báo tự đổi mới hình thức thể hiện để bắt kịp xu hướng chung.
		<word>cạnh</word>
		<word>cơ quan</word>
		<word>báo chí</word>
		<word>báo</word>
		<word>đổi mới</word>
		<word>hình thức</word>
		<word>thể hiện</word>
		<word>bắt</word>
		<word>kịp</word>
		<word>xu hướng</word>
	</sentence>
</document>
